aristech_stt_client/__init__.py
aristech_stt_client/client.py
aristech_stt_client/proto/__init__.py
aristech_stt_client/proto/stt_service_pb2.py
aristech_stt_client/proto/stt_service_pb2.pyi
aristech_stt_client/proto/stt_service_pb2_grpc.py
aristech_stt_client-2.2.0.dist-info/METADATA
aristech_stt_client-2.2.0.dist-info/WHEEL
aristech_stt_client-2.2.0.dist-info/top_level.txt
aristech_stt_client-2.2.0.dist-info/RECORD
