Metadata-Version: 2.4
Name: aristech-stt-client
Version: 2.2.0
Summary: A Python client library for the Aristech Speech-to-Text API
Author-email: Martin Mende <speech@aristech.de>
License: MIT License
Project-URL: Homepage, https://github.com/aristech-de/stt-clients/tree/main/python
Project-URL: Issues, https://github.com/aristech-de/stt-clients/issues
Classifier: Programming Language :: Python :: 3
Classifier: License :: OSI Approved :: MIT License
Classifier: Operating System :: OS Independent
Requires-Dist: grpcio<2.0.0,>=1.71.0
Requires-Dist: protobuf<7.0.0,>=5.26.1
Provides-Extra: dev
Requires-Dist: grpcio-tools<2.0.0,>=1.71.0; extra == "dev"
Requires-Dist: mypy-protobuf<4.0.0,>=3.6.0; extra == "dev"
Requires-Dist: python-dotenv<2.0.0,>=1.1.0; extra == "dev"
